fastcook/__init__.py
fastcook/_nbdev.py
fastcook/notebook.py
fastcook/utils.py
fastcook/common/__init__.py
fastcook/common/callbacks.py
fastcook/common/clean_data.py
fastcook/common/datablock.py
fastcook/common/typedispatch.py
fastcook/plataforms/__init__.py
fastcook/plataforms/colab.py
fastcook/vision/__init__.py
fastcook/vision/basic.py
fastcook-0.0.1.dist-info/LICENSE
fastcook-0.0.1.dist-info/METADATA
fastcook-0.0.1.dist-info/WHEEL
fastcook-0.0.1.dist-info/entry_points.txt
fastcook-0.0.1.dist-info/top_level.txt
fastcook-0.0.1.dist-info/RECORD
