Metadata-Version: 2.1
Name: fastcook
Version: 0.0.1
Summary: fastcook provides useful recipes for your fastai driven workflow.
Home-page: https://github.com/lgvaz/fastcook
Author: Lucas Goulart Vazquez
Author-email: lgvaz42@gmail.com
License: Apache Software License 2.0
Keywords: fastai cookbook
Platform: UNKNOWN
Classifier: Development Status :: 3 - Alpha
Classifier: Intended Audience :: Developers
Classifier: License :: OSI Approved :: Apache Software License
Classifier: Natural Language :: English
Classifier: Programming Language :: Python :: 3.6
Classifier: Programming Language :: Python :: 3.7
Classifier: Programming Language :: Python :: 3.8
Requires-Python: >=3.6
Requires-Dist: fastai2
